getkeyforgeumyung/getsentence.py
getkeyforgeumyung-0.0.0.1.dist-info/METADATA
getkeyforgeumyung-0.0.0.1.dist-info/WHEEL
getkeyforgeumyung-0.0.0.1.dist-info/top_level.txt
getkeyforgeumyung-0.0.0.1.dist-info/RECORD
