Metadata-Version: 2.1
Name: getkeyforgeumyung
Version: 0.0.0.1
Summary: when you input your keyword, you can get sentence including the keyword you input.
Home-page: UNKNOWN
Author: Jisung Ha
Author-email: serendipi27@gmail.com
License: MIT
Platform: UNKNOWN
Requires-Python: >=3
